un_bound_histogram/__init__.py
un_bound_histogram/bins_utils.py
un_bound_histogram/version.py
un_bound_histogram-0.1.0.dist-info/licenses/LICENSE
un_bound_histogram-0.1.0.dist-info/METADATA
un_bound_histogram-0.1.0.dist-info/WHEEL
un_bound_histogram-0.1.0.dist-info/top_level.txt
un_bound_histogram-0.1.0.dist-info/RECORD
