Metadata-Version: 2.4
Name: un_bound_histogram
Version: 0.1.0
Summary: Histogram data in bins but there are 2**64 (almost un-bound) bins.
Home-page: https://github.com/cherenkov-plenoscope/un_bound_histogram
Author: Sebastian Achim Mueller
Author-email: sebastian-achim.mueller@mpi-hd.mpg.de
Classifier: Programming Language :: Python :: 3
Classifier: License :: OSI Approved :: MIT License
Classifier: Operating System :: OS Independent
Classifier: Natural Language :: English
License-File: LICENSE
Dynamic: author
Dynamic: author-email
Dynamic: classifier
Dynamic: description
Dynamic: description-content-type
Dynamic: home-page
Dynamic: license-file
Dynamic: summary
